admin_reorder/__init__.py
admin_reorder/middleware.py
admin_reorder/models.py
admin_reorder/static/css/admin-reorder.css
admin_reorder/static/js/admin-reorder.js
admin_reorder/templates/admin-reorder/base.html
django_reorder_admin-0.3.1.dist-info/AUTHORS.rst
django_reorder_admin-0.3.1.dist-info/LICENSE
django_reorder_admin-0.3.1.dist-info/METADATA
django_reorder_admin-0.3.1.dist-info/WHEEL
django_reorder_admin-0.3.1.dist-info/top_level.txt
django_reorder_admin-0.3.1.dist-info/RECORD
