Metadata-Version: 2.1
Name: django-reorder-admin
Version: 0.3.1
Summary: Custom ordering for the apps and models in the admin app.
Home-page: https://github.com/mishbahr/django-modeladmin-reorder
Author: Nurbergen Khinatolla
Author-email: nhinatolla@gmail.com
License: BSD
Keywords: django-modeladmin-reorder
Platform: UNKNOWN
Classifier: Development Status :: 2 - Pre-Alpha
Classifier: Framework :: Django
Classifier: Intended Audience :: Developers
Classifier: License :: OSI Approved :: BSD License
Classifier: Natural Language :: English
Classifier: Programming Language :: Python :: 2.7
Classifier: Programming Language :: Python :: 3.4
Classifier: Programming Language :: Python :: 3.5
License-File: LICENSE
License-File: AUTHORS.rst
Requires-Dist: django
